drugstone/__init__.py
drugstone/deep_search.py
drugstone/new_task.py
drugstone/new_tasks.py
drugstone/scripts/__init__.py
drugstone/scripts/add_edges_to_genes.py
drugstone/scripts/check_result_size.py
drugstone/scripts/fetch_edges.py
drugstone/scripts/map_nodes_to_internal_ids.py
drugstone/scripts/merge_results.py
drugstone/scripts/normalize_nodes.py
drugstone/scripts/normalize_task_parameter.py
drugstone/scripts/request_task_info.py
drugstone/scripts/request_task_result.py
drugstone/scripts/start_task.py
drugstone/scripts/task_id.py
drugstone/scripts/wait_for_task_to_finish.py
drugstone/scripts/constants/__init__.py
drugstone/scripts/constants/task_parameter.py
drugstone/scripts/constants/url.py
drugstone/task/__init__.py
drugstone/task/task.py
drugstone/task/task_result.py
drugstone/task/tasks.py
drugstone/task/tasks_result.py
drugstone/task/models/__init__.py
drugstone/task/models/drug.py
drugstone/task/models/gene.py
drugstone/task/scripts/__init__.py
drugstone/task/scripts/create_path.py
drugstone/task/scripts/download_network_graph.py
drugstone/task/scripts/make_upsetplot.py
drugstone-0.0.2.dist-info/LICENSE
drugstone-0.0.2.dist-info/METADATA
drugstone-0.0.2.dist-info/WHEEL
drugstone-0.0.2.dist-info/top_level.txt
drugstone-0.0.2.dist-info/RECORD
