Metadata-Version: 2.1
Name: drugstone
Version: 0.0.2
Summary: The python package for the https://drugst.one/ platform.
Home-page: https://github.com/t-ugur/drugstone.git
Author: Ugur Turhan
License: UNKNOWN
Platform: UNKNOWN
Classifier: Programming Language :: Python :: 3
Classifier: License :: OSI Approved :: MIT License
Classifier: Operating System :: OS Independent
Requires-Python: >=3.6
License-File: LICENSE
Requires-Dist: urllib3
Requires-Dist: requests
Requires-Dist: pandas
Requires-Dist: pyvis
Requires-Dist: upsetplot
